polyfactory/__init__.py
polyfactory/__metadata__.py
polyfactory/collection_extender.py
polyfactory/constants.py
polyfactory/decorators.py
polyfactory/exceptions.py
polyfactory/field_meta.py
polyfactory/fields.py
polyfactory/persistence.py
polyfactory/py.typed
polyfactory/pytest_plugin.py
polyfactory/factories/__init__.py
polyfactory/factories/attrs_factory.py
polyfactory/factories/base.py
polyfactory/factories/beanie_odm_factory.py
polyfactory/factories/dataclass_factory.py
polyfactory/factories/msgspec_factory.py
polyfactory/factories/odmantic_odm_factory.py
polyfactory/factories/pydantic_factory.py
polyfactory/factories/sqlalchemy_factory.py
polyfactory/factories/typed_dict_factory.py
polyfactory/utils/__init__.py
polyfactory/utils/_internal.py
polyfactory/utils/deprecation.py
polyfactory/utils/helpers.py
polyfactory/utils/model_coverage.py
polyfactory/utils/normalize_type.py
polyfactory/utils/predicates.py
polyfactory/utils/types.py
polyfactory/value_generators/__init__.py
polyfactory/value_generators/complex_types.py
polyfactory/value_generators/constrained_collections.py
polyfactory/value_generators/constrained_dates.py
polyfactory/value_generators/constrained_numbers.py
polyfactory/value_generators/constrained_path.py
polyfactory/value_generators/constrained_strings.py
polyfactory/value_generators/constrained_url.py
polyfactory/value_generators/constrained_uuid.py
polyfactory/value_generators/primitives.py
polyfactory/value_generators/regex.py
polyfactory-2.22.4.dist-info/METADATA
polyfactory-2.22.4.dist-info/WHEEL
polyfactory-2.22.4.dist-info/licenses/LICENSE
polyfactory-2.22.4.dist-info/RECORD
