Metadata-Version: 2.4
Name: polyfactory
Version: 2.22.4
Summary: Mock data generation factories
Project-URL: Issue Tracker, https://github.com/litestar-org/polyfactory/issues?q=is%3Aissue+is%3Aopen+sort%3Aupdated-desc
Project-URL: Changelog, https://github.com/litestar-org/polyfactory/releases/
Project-URL: Twitter, https://twitter.com/LitestarAPI
Project-URL: Reddit, https://www.reddit.com/r/LitestarAPI
Project-URL: Discord, https://discord.gg/MmcwxztmQb
Project-URL: Blog, https://blog.litestar.dev
Project-URL: homepage, https://github.com/litestar-org/polyfactory
Project-URL: repository, https://github.com/litestar-org/polyfactory
Project-URL: documentation, https://github.com/litestar-org/polyfactory
Author-email: Na'aman Hirschfeld <nhirschfeld@gmail.com>
Maintainer-email: Visakh Unnikrishnan <guacs@litestar.dev>, Cody Fincher <cody@litestar.dev>, Janek Nouvertné <janek@litestar.dev>, Jacob Coffee <jacob@litestar.dev>, Peter Schutt <peter@litestar.dev>, Alc <alc@litestar.dev>, Andy <adh.truong@gmail.com>
License: MIT
License-File: LICENSE
Keywords: attrs,dataclasses,msgspec,pydantic,sqlalchemy
Classifier: Development Status :: 5 - Production/Stable
Classifier: Environment :: Web Environment
Classifier: Framework :: Pytest
Classifier: Intended Audience :: Developers
Classifier: License :: OSI Approved :: MIT License
Classifier: Natural Language :: English
Classifier: Operating System :: OS Independent
Classifier: Programming Language :: Python
Classifier: Programming Language :: Python :: 3.8
Classifier: Programming Language :: Python :: 3.9
Classifier: Programming Language :: Python :: 3.10
Classifier: Programming Language :: Python :: 3.11
Classifier: Programming Language :: Python :: 3.12
Classifier: Programming Language :: Python :: 3.13
Classifier: Topic :: Software Development
Classifier: Topic :: Software Development :: Libraries
Classifier: Topic :: Software Development :: Testing
Classifier: Topic :: Software Development :: Testing :: Unit
Classifier: Topic :: Utilities
Classifier: Typing :: Typed
Requires-Python: <4.0,>=3.8
Requires-Dist: faker>=5.0.0
Requires-Dist: typing-extensions>=4.6.0
Provides-Extra: attrs
Requires-Dist: attrs>=22.2.0; extra == 'attrs'
Provides-Extra: beanie
Requires-Dist: beanie; extra == 'beanie'
Requires-Dist: pydantic[email]; extra == 'beanie'
Requires-Dist: pymongo<4.9; extra == 'beanie'
Provides-Extra: full
Requires-Dist: attrs; extra == 'full'
Requires-Dist: beanie; extra == 'full'
Requires-Dist: msgspec; extra == 'full'
Requires-Dist: odmantic; extra == 'full'
Requires-Dist: pydantic; extra == 'full'
Requires-Dist: sqlalchemy; extra == 'full'
Provides-Extra: msgspec
Requires-Dist: msgspec; extra == 'msgspec'
Provides-Extra: odmantic
Requires-Dist: odmantic<1.0.0; extra == 'odmantic'
Requires-Dist: pydantic[email]; extra == 'odmantic'
Provides-Extra: pydantic
Requires-Dist: pydantic[email]>=1.10; extra == 'pydantic'
Provides-Extra: sqlalchemy
Requires-Dist: sqlalchemy>=1.4.29; extra == 'sqlalchemy'
